CHANGES.txt
LICENSE.txt
MANIFEST.in
README.rst
requirements.txt
setup.py
distributed_task/__init__.py
distributed_task/apps.py
distributed_task/exceptions.py
distributed_task/models.py
distributed_task/settings.py
distributed_task/broker/__init__.py
distributed_task/broker/interface.py
distributed_task/broker/utils.py
distributed_task/broker/backends/__init__.py
distributed_task/broker/backends/amqp.py
distributed_task/broker/backends/db.py
distributed_task/broker/backends/dummy.py
distributed_task/core/__init__.py
distributed_task/core/decorators.py
distributed_task/core/handler.py
distributed_task/core/serializer.py
distributed_task/management/__init__.py
distributed_task/management/commands/__init__.py
distributed_task/management/commands/run_worker.py
distributed_task/task/__init__.py
distributed_task/task/loader.py
distributed_task/task/registry.py
distributed_task/tests/__init__.py
distributed_task/tests/test_basics.py
distributed_task/tests/test_decorators.py
distributed_task/tests/test_serialization.py
distributed_task/utils/__init__.py
distributed_task/utils/module_loading.py
django_distributed_task.egg-info/PKG-INFO
django_distributed_task.egg-info/SOURCES.txt
django_distributed_task.egg-info/dependency_links.txt
django_distributed_task.egg-info/requires.txt
django_distributed_task.egg-info/top_level.txt