Metadata-Version: 1.1
Name: django-distributed-task
Version: 1.0.0
Summary: Django application to delegate tasks asynchronously to worker processes.
Home-page: http://pypi.python.org/pypi/django-distributed-task/
Author: Marc Riegel
Author-email: mail@marclab.de
License: MIT
Platform: UNKNOWN
Classifier: Development Status :: 4 - Beta
Classifier: License :: OSI Approved :: MIT License
Classifier: Topic :: System :: Distributed Computing
Classifier: Topic :: Software Development :: Object Brokering
Classifier: Programming Language :: Python
Classifier: Programming Language :: Python :: 2
Classifier: Programming Language :: Python :: 2.7
Classifier: Programming Language :: Python :: 3
Classifier: Programming Language :: Python :: 3.3
Classifier: Programming Language :: Python :: 3.4
Classifier: Framework :: Django
Classifier: Operating System :: Unix
